docker_runcheck/__init__.py
docker_runcheck/app.py
docker_runcheck-0.1.7.dist-info/METADATA
docker_runcheck-0.1.7.dist-info/WHEEL
docker_runcheck-0.1.7.dist-info/entry_points.txt
docker_runcheck-0.1.7.dist-info/RECORD
