Metadata-Version: 2.3
Name: docker_runcheck
Version: 0.1.7
Summary: An application to parse Dockerfiles and determine whether all called binaries are able to run (are either present in the base image or are installed by a package manager)
License: MIT
Author: Paulo Aragao
Author-email: paulo.aragao.dev@gmail.com
Requires-Python: >=3.13,<4.0
Classifier: License :: OSI Approved :: MIT License
Classifier: Programming Language :: Python :: 3
Classifier: Programming Language :: Python :: 3.13
Requires-Dist: docker (>=7.1.0,<8.0.0)
Requires-Dist: dockerfile (>=3.2.0,<4.0.0)
Requires-Dist: rich (>=13.9.4,<14.0.0)
Requires-Dist: typer (>=0.15.1,<0.16.0)
